Changelog.rst
Developer_Manual.rst
LICENSE.txt
MANIFEST.in
README.rst
pyproject.toml
setup.cfg
setup.py
NexiaX.egg-info/PKG-INFO
NexiaX.egg-info/SOURCES.txt
NexiaX.egg-info/dependency_links.txt
NexiaX.egg-info/entry_points.txt
NexiaX.egg-info/not-zip-safe
NexiaX.egg-info/requires.txt
NexiaX.egg-info/top_level.txt
bin/autoformat-qutayba-source
bin/check-qutayba-with-pylint
bin/compare_with_cpython
bin/compare_with_xml
bin/measure-construct-performance
bin/qutayba
bin/qutayba-run
doc/qutayba-run.1
doc/qutayba.1
doc/Logo/nexium-Logo-Symbol.svg
doc/images/nexium-Logo-Horizontal.png
doc/images/nexium-Logo-Symbol.png
doc/images/nexium-Logo-Vertical.png
lib/hints.py
misc/nexium-run.cmd
misc/nexium.cmd
misc/qutayba-run.cmd
misc/qutayba.cmd
qutayba/Builtins.py
qutayba/BytecodeCaching.py
qutayba/Bytecodes.py
qutayba/CacheCleanup.py
qutayba/Constants.py
qutayba/EncryptedNexia.py
qutayba/Errors.py
qutayba/HardImportRegistry.py
qutayba/MainControl.py
qutayba/ModuleRegistry.py
qutayba/OptionParsing.py
qutayba/Options.py
qutayba/OutputDirectories.py
qutayba/PostProcessing.py
qutayba/Progress.py
qutayba/PythonFlavors.py
qutayba/PythonOperators.py
qutayba/PythonVersions.py
qutayba/Serialization.py
qutayba/SourceCodeReferences.py
qutayba/Tracing.py
qutayba/TreeXML.py
qutayba/Variables.py
qutayba/Version.py
qutayba/__init__.py
qutayba/__main__.py
qutayba/__past__.py
qutayba/build/Backend.scons
qutayba/build/CCompilerVersion.scons
qutayba/build/DataComposerInterface.py
qutayba/build/Offsets.scons
qutayba/build/Onefile.scons
qutayba/build/SconsCaching.py
qutayba/build/SconsCompilerSettings.py
qutayba/build/SconsHacks.py
qutayba/build/SconsInterface.py
qutayba/build/SconsProgress.py
qutayba/build/SconsSpawn.py
qutayba/build/SconsUtils.py
qutayba/build/__init__.py
qutayba/build/include/qutayba/allocator.h
qutayba/build/include/qutayba/builtins.h
qutayba/build/include/qutayba/calling.h
qutayba/build/include/qutayba/checkers.h
qutayba/build/include/qutayba/checksum_tools.h
qutayba/build/include/qutayba/compiled_asyncgen.h
qutayba/build/include/qutayba/compiled_cell.h
qutayba/build/include/qutayba/compiled_coroutine.h
qutayba/build/include/qutayba/compiled_frame.h
